design.plone.policy-5.0.19-py3.11-nspkg.pth
design/plone/policy/__init__.py
design/plone/policy/configure.zcml
design/plone/policy/interfaces.py
design/plone/policy/permissions.zcml
design/plone/policy/rejectanonymous.py
design/plone/policy/sensitive.py
design/plone/policy/setuphandlers.py
design/plone/policy/testing.py
design/plone/policy/upgrades.py
design/plone/policy/upgrades.zcml
design/plone/policy/utils.py
design/plone/policy/browser/__init__.py
design/plone/policy/browser/config.py
design/plone/policy/browser/configure.zcml
design/plone/policy/browser/trasparenza.py
design/plone/policy/limit_root_addables/__init__.py
design/plone/policy/limit_root_addables/configure.zcml
design/plone/policy/limit_root_addables/setuphandlers.py
design/plone/policy/limit_root_addables/profiles/default/types/Plone_Site.xml
design/plone/policy/locales/README.rst
design/plone/policy/locales/__init__.py
design/plone/policy/locales/design.plone.policy.pot
design/plone/policy/locales/update.py
design/plone/policy/locales/update.sh
design/plone/policy/locales/en/LC_MESSAGES/design.plone.policy.po
design/plone/policy/patches/__init__.py
design/plone/policy/patches/collective_volto_formsupport.py
design/plone/policy/profiles/default/actions.xml
design/plone/policy/profiles/default/browserlayer.xml
design/plone/policy/profiles/default/catalog.xml
design/plone/policy/profiles/default/metadata.xml
design/plone/policy/profiles/default/registry.xml
design/plone/policy/profiles/default/rolemap.xml
design/plone/policy/profiles/uninstall/browserlayer.xml
design/plone/policy/profiles/uninstall/registry.xml
design/plone/policy/restapi/__init__.py
design/plone/policy/restapi/configure.zcml
design/plone/policy/restapi/bandi_search_filters/__init__.py
design/plone/policy/restapi/bandi_search_filters/configure.zcml
design/plone/policy/restapi/bandi_search_filters/get.py
design/plone/policy/restapi/search_filters/__init__.py
design/plone/policy/restapi/search_filters/configure.zcml
design_plone_policy-5.0.19.dist-info/licenses/LICENSE.GPL
design_plone_policy-5.0.19.dist-info/licenses/LICENSE.rst
design_plone_policy-5.0.19.dist-info/METADATA
design_plone_policy-5.0.19.dist-info/WHEEL
design_plone_policy-5.0.19.dist-info/entry_points.txt
design_plone_policy-5.0.19.dist-info/namespace_packages.txt
design_plone_policy-5.0.19.dist-info/top_level.txt
design_plone_policy-5.0.19.dist-info/RECORD
