Metadata-Version: 2.4
Name: design.plone.policy
Version: 5.0.19
Summary: Pacchetto per creare un sito Agid su Plone
Home-page: https://github.com/collective/design.plone.policy
Author: RedTurtle Technology
Author-email: sviluppo@redturtle.it
License: GPL version 2
Project-URL: PyPI, https://pypi.python.org/pypi/design.plone.policy
Project-URL: Source, https://github.com/RedTurtle/design.plone.policy
Project-URL: Tracker, https://github.com/RedTurtle/design.plone.policy/issues
Keywords: Python Plone
Classifier: Development Status :: 5 - Production/Stable
Classifier: Environment :: Web Environment
Classifier: Framework :: Plone
Classifier: Framework :: Plone :: Addon
Classifier: Framework :: Plone :: 6.0
Classifier: Programming Language :: Python
Classifier: Programming Language :: Python :: 3.11
Classifier: Operating System :: OS Independent
Classifier: License :: OSI Approved :: GNU General Public License v2 (GPLv2)
Requires-Python: >=3.7
License-File: LICENSE.GPL
License-File: LICENSE.rst
Requires-Dist: setuptools
Requires-Dist: redturtle.volto
Requires-Dist: design.plone.contenttypes>=6.0.0.dev0
Requires-Dist: collective.feedback
Requires-Dist: collective.volto.dropdownmenu
Requires-Dist: collective.volto.formsupport[honeypot]<3.4.0,>=3.3.0
Requires-Dist: collective.volto.secondarymenu
Requires-Dist: collective.volto.socialsettings
Requires-Dist: collective.volto.slimheader
Requires-Dist: collective.volto.subsites
Requires-Dist: collective.volto.subfooter
Requires-Dist: redturtle.voltoplugin.editablefooter
Requires-Dist: redturtle.faq
Requires-Dist: redturtle.rssservice
Requires-Dist: iw.rejectanonymous
Requires-Dist: collective.volto.contactsblock>=1.0.1
Provides-Extra: test
Requires-Dist: plone.app.testing; extra == "test"
Requires-Dist: plone.testing>=5.0.0; extra == "test"
Requires-Dist: plone.app.contenttypes; extra == "test"
Requires-Dist: plone.app.robotframework[debug]; extra == "test"
Requires-Dist: collective.MockMailHost; extra == "test"
Dynamic: author
Dynamic: author-email
Dynamic: classifier
Dynamic: description
Dynamic: home-page
Dynamic: keywords
Dynamic: license
Dynamic: license-file
Dynamic: project-url
Dynamic: provides-extra
Dynamic: requires-dist
Dynamic: requires-python
Dynamic: summary
